aquaparser/__init__.py
aquaparser/__main__.py
aquaparser/py.typed
aquaparser/schemas.py
aquaparser/parsers/__init__.py
aquaparser/parsers/parser.py
aquaparser/parsers/title_parser.py
aquaparser/parsers/toc_parser.py
aqua_parser-0.2.1.dist-info/LICENSE
aqua_parser-0.2.1.dist-info/WHEEL
aqua_parser-0.2.1.dist-info/METADATA
aqua_parser-0.2.1.dist-info/RECORD
